CHANGES.rst
LICENSE.txt
MANIFEST.in
README.rst
setup.cfg
setup.py
h10n/__init__.py
h10n/core.py
h10n/source.py
h10n/translator.py
h10n/util.py
h10n.egg-info/PKG-INFO
h10n.egg-info/SOURCES.txt
h10n.egg-info/dependency_links.txt
h10n.egg-info/entry_points.txt
h10n.egg-info/requires.txt
h10n.egg-info/top_level.txt
h10n.egg-info/zip-safe
h10n/helper/__init__.py
h10n/helper/pluralize.py
h10n/tests/__init__.py
h10n/tests/core_test/__init__.py
h10n/tests/core_test/catalog_test.py
h10n/tests/core_test/helper_namespace_test.py
h10n/tests/core_test/locale_test.py
h10n/tests/core_test/message_test.py
h10n/tests/helper_test/__init__.py
h10n/tests/helper_test/pluralize_test.py
h10n/tests/source_test/__init__.py
h10n/tests/source_test/scanner_test.py
h10n/tests/source_test/yaml_source_test.py
h10n/tests/translator_test/__init__.py
h10n/tests/translator_test/message_test.py
h10n/tests/translator_test/translator_test.py
h10n/tests/util_test/__init__.py
h10n/tests/util_test/exception_context_test.py
h10n/tests/util_test/namespace_test.py